docstring2argparse/__init__.py
docstring2argparse-0.1.2.dist-info/LICENSE
docstring2argparse-0.1.2.dist-info/METADATA
docstring2argparse-0.1.2.dist-info/WHEEL
docstring2argparse-0.1.2.dist-info/top_level.txt
docstring2argparse-0.1.2.dist-info/RECORD
